dataparsers/__init__.md
dataparsers/__init__.py
dataparsers/__init__.pyi
dataparsers/dataparsers.py
dataparsers/py.typed
dataparsers-2.3.3.dist-info/METADATA
dataparsers-2.3.3.dist-info/WHEEL
dataparsers-2.3.3.dist-info/licenses/LICENSE.txt
dataparsers-2.3.3.dist-info/RECORD
