Metadata-Version: 2.4
Name: dataparsers
Version: 2.3.3
Summary: A wrapper around argparse to get command line argument parsers from dataclasses
Project-URL: Documentation, https://dataparsers.readthedocs.io/en/latest/
Project-URL: Source, https://github.com/Diogo-Rossi/dataparsers.git
Project-URL: Issues, https://github.com/Diogo-Rossi/dataparsers/issues
Author-email: Diogo Rossi <rossi.diogo@gmail.com>
License: MIT
License-File: LICENSE.txt
Classifier: Programming Language :: Python :: 3.10
Classifier: Programming Language :: Python :: 3.11
Classifier: Programming Language :: Python :: 3.12
Requires-Python: >=3.10
